siwe/__init__.py
siwe/defs.py
siwe/grammars/__init__.py
siwe/grammars/eip4361.py
siwe/grammars/rfc3339.py
siwe/grammars/rfc5234.py
siwe/parsed.py
siwe/siwe.py
siwe-4.3.0.dist-info/METADATA
siwe-4.3.0.dist-info/WHEEL
siwe-4.3.0.dist-info/RECORD
