Metadata-Version: 2.1
Name: siwe
Version: 4.3.0
Summary: A Python implementation of Sign-In with Ethereum (EIP-4361).
Home-page: https://login.xyz
License: MIT OR Apache-2.0
Keywords: SIWE,EIP-4361,Sign-In with Ethereum,Spruce ID
Author: Spruce Systems, Inc.
Author-email: hello@spruceid.com
Requires-Python: >=3.8,<4.0
Classifier: License :: Other/Proprietary License
Classifier: Programming Language :: Python :: 3
Classifier: Programming Language :: Python :: 3.8
Classifier: Programming Language :: Python :: 3.9
Classifier: Programming Language :: Python :: 3.10
Classifier: Programming Language :: Python :: 3.11
Classifier: Programming Language :: Python :: 3.12
Requires-Dist: abnf (>=2.2,<3)
Requires-Dist: eth-account (>=0.13.1,<0.14)
Requires-Dist: eth-typing (>=3.4.0)
Requires-Dist: eth-utils (>=2.2.0)
Requires-Dist: pydantic (>=2.7,<3)
Requires-Dist: pydantic-core (>=2,<3)
Requires-Dist: typing-extensions (>=4,<5)
Requires-Dist: web3 (>=7.3.0,<8)
Project-URL: Discord, https://discord.gg/Sf9tSFzrnt
Project-URL: EIP, https://github.com/ethereum/EIPs/blob/master/EIPS/eip-4361.md
Project-URL: Repository, https://github.com/spruceid/siwe-py
